no_cluely/__init__.py
no_cluely/libno_cluely_driver.dylib
no_cluely/py.typed
no_cluely-0.0.4.dist-info/METADATA
no_cluely-0.0.4.dist-info/WHEEL
no_cluely-0.0.4.dist-info/top_level.txt
no_cluely-0.0.4.dist-info/RECORD
