Metadata-Version: 2.4
Name: no-cluely
Version: 0.0.4
Summary: Detect Cluely cheating software and its evasion techniques
Author: TerminalSin
License: MIT
Project-URL: Homepage, https://github.com/terminalsin/no-cluely
Project-URL: Bug Reports, https://github.com/terminalsin/no-cluely/issues
Project-URL: Source, https://github.com/terminalsin/no-cluely
Project-URL: Documentation, https://github.com/terminalsin/no-cluely#readme
Keywords: privacy,monitoring,detection,cluely,employee,screen-sharing,evasion,macos
Classifier: Development Status :: 4 - Beta
Classifier: Intended Audience :: Developers
Classifier: Intended Audience :: System Administrators
Classifier: License :: OSI Approved :: MIT License
Classifier: Operating System :: MacOS
Classifier: Programming Language :: Python :: 3
Classifier: Programming Language :: Python :: 3.8
Classifier: Programming Language :: Python :: 3.9
Classifier: Programming Language :: Python :: 3.10
Classifier: Programming Language :: Python :: 3.11
Classifier: Programming Language :: Python :: 3.12
Classifier: Topic :: Security
Classifier: Topic :: System :: Monitoring
Classifier: Topic :: Software Development :: Libraries :: Python Modules
Requires-Python: >=3.8
Requires-Dist: typing-extensions>=4.0.0
Provides-Extra: dev
Requires-Dist: pytest>=7.0.0; extra == "dev"
Requires-Dist: pytest-cov>=4.0.0; extra == "dev"
Requires-Dist: black>=22.0.0; extra == "dev"
Requires-Dist: mypy>=1.0.0; extra == "dev"
Requires-Dist: flake8>=5.0.0; extra == "dev"
